conductor/__init__.py
linklabs_conductor-1.5.4.dist-info/METADATA
linklabs_conductor-1.5.4.dist-info/RECORD
linklabs_conductor-1.5.4.dist-info/WHEEL
linklabs_conductor-1.5.4.dist-info/top_level.txt
