Metadata-Version: 2.1
Name: linklabs-conductor
Version: 1.5.4
Summary: Linklabs Conductor API Wrapper
Home-page: https://www.link-labs.com
Author: Linklabs, LLC
Author-email: support@link-labs.com
License: MIT
Requires-Dist: requests
Requires-Dist: python-dateutil
Requires-Dist: ws4py
